{
  "id": 160210,
  "name": "旅街レイトショー",
  "name_cn": "旅街晚间秀",
  "summary": " 「別れ」や「旅立ち」、甘酸っぱい後悔やどうしようもなかった出来事。 その先にある“いま”をそっと肯定し、慰め、また前へ進むための4つの物語を描きます！",
  "date": "2016-01-08",
  "platform": "TV",
  "images": {
    "large": "//lain.bgm.tv/pic/cover/l/60/78/160210_6qT66.jpg",
    "common": "//lain.bgm.tv/r/400/pic/cover/l/60/78/160210_6qT66.jpg"
  },
  "eps": 4,
  "rating": {
    "rank": 4050,
    "total": 189,
    "count": {
      "1": 0,
      "2": 0,
      "3": 1,
      "4": 3,
      "5": 19,
      "6": 60,
      "7": 83,
      "8": 18,
      "9": 3,
      "10": 2
    },
    "score": 6.6
  },
  "tags": [
    {
      "name": "泡面番",
      "count": 78
    },
    {
      "name": "2016年1月",
      "count": 58
    },
    {
      "name": "TV",
      "count": 49
    },
    {
      "name": "2016",
      "count": 36
    },
    {
      "name": "CoMixWaveFilms",
      "count": 36
    },
    {
      "name": "原创",
      "count": 33
    },
    {
      "name": "治愈",
      "count": 32
    },
    {
      "name": "日常",
      "count": 23
    },
    {
      "name": "沼田友",
      "count": 15
    },
    {
      "name": "旅街晚间秀",
      "count": 14
    },
    {
      "name": "泡面",
      "count": 9
    },
    {
      "name": "2016年一月番",
      "count": 7
    },
    {
      "name": "2016年",
      "count": 6
    },
    {
      "name": "CoMix_Wave_Films",
      "count": 5
    },
    {
      "name": "短片",
      "count": 3
    },
    {
      "name": "CoMixWave",
      "count": 3
    },
    {
      "name": "ppt",
      "count": 2
    },
    {
      "name": "日本动画",
      "count": 2
    },
    {
      "name": "感人",
      "count": 2
    },
    {
      "name": "温情",
      "count": 2
    },
    {
      "name": "2016年上半年",
      "count": 1
    },
    {
      "name": "别离",
      "count": 1
    },
    {
      "name": "旅街LateShow",
      "count": 1
    },
    {
      "name": "7+",
      "count": 1
    },
    {
      "name": "201601",
      "count": 1
    },
    {
      "name": "总之去看1",
      "count": 1
    },
    {
      "name": "USAT",
      "count": 1
    },
    {
      "name": "里見篤",
      "count": 1
    },
    {
      "name": "星子旋風脚",
      "count": 1
    },
    {
      "name": "2016年Web·SP",
      "count": 1
    }
  ],
  "locked": false,
  "sites": [
    {
      "site": "bangumi",
      "id": "160210"
    },
    {
      "site": "nicovideo",
      "id": "tabimachi",
      "begin": "2016-01-08T15:00:00.000Z",
      "broadcast": "R/2016-01-08T15:00:00.000Z/P7D"
    },
    {
      "site": "bilibili",
      "id": "3286",
      "begin": "2016-01-07T16:00:00.000Z",
      "broadcast": "R/2016-01-12T10:56:05.000Z/P7D"
    },
    {
      "site": "unext",
      "id": "SID0021402",
      "begin": "2017-05-08T03:00:00.000Z",
      "broadcast": "R/2017-05-08T03:00:00.000Z/P7D"
    },
    {
      "site": "dmhy",
      "id": "旅街"
    },
    {
      "site": "bangumi_moe",
      "id": "56857e58d4d7dbf20b597c42"
    }
  ]
}