{
  "id": 425591,
  "name": "アンデッドガール・マーダーファルス",
  "name_cn": "不死少女 杀人笑剧",
  "summary": "吸血鬼及人造人、怪盗、狼人、开膛手，还有名侦探。异形蠢动的十九世纪末欧洲，人类亲和派的吸血鬼遭到银桩贯穿虐杀死亡。找来解决此案的，是专门处理人类避之唯恐不及的「怪物案件」的专门侦探轮堂鸦夜，以及带着奇怪鸟笼的男人真打津轻。他们从留存的线索和怪物才具备的特性导出推理。充满谜团宛如噩梦的笑剧，在此开幕！",
  "date": "2023-07-05",
  "platform": "TV",
  "images": {
    "large": "//lain.bgm.tv/pic/cover/l/6b/c0/425591_Llbje.jpg",
    "common": "//lain.bgm.tv/r/400/pic/cover/l/6b/c0/425591_Llbje.jpg"
  },
  "eps": 13,
  "rating": {
    "rank": 1471,
    "total": 4450,
    "count": {
      "1": 4,
      "2": 4,
      "3": 10,
      "4": 27,
      "5": 101,
      "6": 552,
      "7": 1865,
      "8": 1665,
      "9": 181,
      "10": 41
    },
    "score": 7.3
  },
  "tags": [
    {
      "name": "推理",
      "count": 1307
    },
    {
      "name": "2023年7月",
      "count": 1069
    },
    {
      "name": "悬疑",
      "count": 1010
    },
    {
      "name": "TV",
      "count": 677
    },
    {
      "name": "奇幻",
      "count": 592
    },
    {
      "name": "LapinTrack",
      "count": 571
    },
    {
      "name": "小说改",
      "count": 503
    },
    {
      "name": "轻小说改",
      "count": 435
    },
    {
      "name": "2023",
      "count": 405
    },
    {
      "name": "畠山守",
      "count": 328
    },
    {
      "name": "轻改",
      "count": 234
    },
    {
      "name": "黒沢ともよ",
      "count": 116
    },
    {
      "name": "青崎有吾",
      "count": 89
    },
    {
      "name": "小俣真一",
      "count": 85
    },
    {
      "name": "战斗",
      "count": 75
    },
    {
      "name": "高木登",
      "count": 27
    },
    {
      "name": "怪异",
      "count": 14
    },
    {
      "name": "2023年",
      "count": 11
    },
    {
      "name": "剧情",
      "count": 10
    },
    {
      "name": "ラパントラック",
      "count": 10
    },
    {
      "name": "小中千昭",
      "count": 10
    },
    {
      "name": "日本",
      "count": 9
    },
    {
      "name": "黑泽朋世",
      "count": 7
    },
    {
      "name": "不死少女",
      "count": 7
    },
    {
      "name": "动画",
      "count": 6
    },
    {
      "name": "TVA",
      "count": 6
    },
    {
      "name": "2020s",
      "count": 5
    },
    {
      "name": "季番",
      "count": 5
    },
    {
      "name": "7月",
      "count": 4
    },
    {
      "name": "群像",
      "count": 4
    }
  ],
  "locked": false
}