{
  "id": 343656,
  "name": "阿波連さんははかれない",
  "name_cn": "测不准的阿波连同学",
  "summary": "阿波连玲奈是一个身材娇小，安静的女孩子，\r\n有点不太擅长把握与他人之间的距离。\r\n\r\n这让坐在隔壁座位的来堂同学，总觉得到有种距离感。\r\n\r\n有一天，来堂同学捡起了阿波连同学掉在地上的橡皮，\r\n以此为契机两人之间的距离开始急速接近！？\r\n\r\n“时而太远”“时而太近”，阿波连同学难以预测。\r\n\r\n各种意义上“测不准”的紧贴系？\r\n青春恋爱喜剧开幕了！\r\n\r\n\r\n小柄で物静かな女の子、 阿波連れいなさん。\r\n人との距離をはかるのが少し苦手。\r\n\r\nそんな彼女の隣の席に座るライドウくんは、\r\n阿波連さんとの間に距離を感じていた。\r\n\r\nある日、阿波連さんが落としてしまった消しゴムを\r\nライドウくんが拾ったことをキッカケに、ふたりの距離は急接近！？\r\n\r\n「遠すぎたり」「近すぎたり」予測不能な阿波連さん。\r\n\r\n色んな意味で、『はかれない』密着系？\r\n青春ラブコメディの幕が上がる！！",
  "date": "2022-04-01",
  "platform": "TV",
  "images": {
    "large": "//lain.bgm.tv/pic/cover/l/bd/15/343656_j6eWd.jpg",
    "common": "//lain.bgm.tv/r/400/pic/cover/l/bd/15/343656_j6eWd.jpg"
  },
  "eps": 12,
  "rating": {
    "rank": 5558,
    "total": 3681,
    "count": {
      "1": 9,
      "2": 8,
      "3": 23,
      "4": 129,
      "5": 470,
      "6": 1369,
      "7": 1222,
      "8": 345,
      "9": 31,
      "10": 75
    },
    "score": 6.4
  },
  "tags": [
    {
      "name": "恋爱",
      "count": 1154
    },
    {
      "name": "校园",
      "count": 895
    },
    {
      "name": "2022年4月",
      "count": 874
    },
    {
      "name": "日常",
      "count": 745
    },
    {
      "name": "漫画改",
      "count": 685
    },
    {
      "name": "搞笑",
      "count": 639
    },
    {
      "name": "TV",
      "count": 432
    },
    {
      "name": "FelixFilm",
      "count": 384
    },
    {
      "name": "萌",
      "count": 317
    },
    {
      "name": "2022",
      "count": 282
    },
    {
      "name": "漫改",
      "count": 235
    },
    {
      "name": "水瀬いのり",
      "count": 152
    },
    {
      "name": "bilibili",
      "count": 86
    },
    {
      "name": "神前暁",
      "count": 60
    },
    {
      "name": "牧野友映",
      "count": 44
    },
    {
      "name": "治愈",
      "count": 20
    },
    {
      "name": "日本",
      "count": 12
    },
    {
      "name": "2022年",
      "count": 12
    },
    {
      "name": "萝莉",
      "count": 11
    },
    {
      "name": "狗粮",
      "count": 11
    },
    {
      "name": "测不准的阿波连同学",
      "count": 10
    },
    {
      "name": "日本动画",
      "count": 9
    },
    {
      "name": "纯爱",
      "count": 8
    },
    {
      "name": "吉岡たかを",
      "count": 5
    },
    {
      "name": "动画",
      "count": 5
    },
    {
      "name": "水濑祈",
      "count": 5
    },
    {
      "name": "吉冈孝夫",
      "count": 5
    },
    {
      "name": "undefined",
      "count": 4
    },
    {
      "name": "神前晓",
      "count": 4
    },
    {
      "name": "工业糖精",
      "count": 4
    }
  ],
  "locked": false
}