{
  "id": 3734,
  "name": "スラムダンク 吠えろバスケットマン魂!!花道と流川の熱き夏",
  "name_cn": "灌篮高手 咆哮吧篮球员的灵魂！！花道和流川的灼热夏季",
  "summary": "流川的后辈一郎的梦想是考入湘北，和流川前辈一起称霸全国。然而，他这个梦想却因为医生的诊断书而面临绝望……",
  "date": "1995-07-15",
  "platform": "剧场版",
  "images": {
    "large": "//lain.bgm.tv/pic/cover/l/9d/75/3734_UzTeY.jpg",
    "common": "//lain.bgm.tv/r/400/pic/cover/l/9d/75/3734_UzTeY.jpg"
  },
  "eps": 1,
  "rating": {
    "rank": 1067,
    "total": 326,
    "count": {
      "1": 1,
      "2": 1,
      "3": 0,
      "4": 0,
      "5": 9,
      "6": 42,
      "7": 116,
      "8": 111,
      "9": 26,
      "10": 20
    },
    "score": 7.5
  },
  "tags": [
    {
      "name": "剧场版",
      "count": 108
    },
    {
      "name": "灌篮高手",
      "count": 73
    },
    {
      "name": "1995",
      "count": 40
    },
    {
      "name": "东映",
      "count": 33
    },
    {
      "name": "体育",
      "count": 21
    },
    {
      "name": "热血",
      "count": 19
    },
    {
      "name": "童年",
      "count": 18
    },
    {
      "name": "SD",
      "count": 15
    },
    {
      "name": "SLAM_DUNK",
      "count": 11
    },
    {
      "name": "补旧番",
      "count": 10
    },
    {
      "name": "JUMP",
      "count": 10
    },
    {
      "name": "运动",
      "count": 8
    },
    {
      "name": "漫画改",
      "count": 8
    },
    {
      "name": "明比正行",
      "count": 7
    },
    {
      "name": "東映アニメーション",
      "count": 6
    },
    {
      "name": "草尾毅",
      "count": 6
    },
    {
      "name": "東映",
      "count": 5
    },
    {
      "name": "竞技",
      "count": 4
    },
    {
      "name": "岸間信明",
      "count": 3
    },
    {
      "name": "篮球",
      "count": 3
    },
    {
      "name": "校园",
      "count": 3
    },
    {
      "name": "漫改",
      "count": 3
    },
    {
      "name": "日本",
      "count": 3
    },
    {
      "name": "アニメ映画",
      "count": 2
    },
    {
      "name": "日本动画",
      "count": 2
    },
    {
      "name": "动画",
      "count": 2
    },
    {
      "name": "大西阳一",
      "count": 2
    },
    {
      "name": "石田彰",
      "count": 2
    },
    {
      "name": "1995年7月",
      "count": 2
    },
    {
      "name": "1995年",
      "count": 2
    }
  ],
  "locked": false,
  "sites": [
    {
      "site": "bangumi",
      "id": "3734"
    },
    {
      "site": "iqiyi",
      "id": "a_19rrhb405h",
      "begin": "2016-02-04T10:33:39.000Z"
    },
    {
      "site": "unext",
      "id": "SID0002663",
      "begin": "2015-02-16T15:00:00.000Z",
      "broadcast": "R/2015-02-16T15:00:00.000Z/P7D"
    }
  ]
}