{
  "id": 110641,
  "name": "うぇいくあっぷがーるZOO!",
  "name_cn": "Wake Up, Girl Zoo!",
  "summary": "2014年8月10日に発表された『Wake Up Girls!』のスピンオフアニメである。略称は「わぐZOO!」。 Wake Up Girls!にはメンバーごとイメージアニマルが設定されており、本編3話等でアニマル天気予報としてイメージアニマルに則したきぐるみを一部のメンバーが着用していた場面がある。 放送媒体等は不明であるが、2014年9月5日にお試し版がYouTubeにて配信された。 仙台市八木山動物公園が協力としてクレジットされており、舞台のモデルとなっているとみられる。\r\n\r\n仙台の校外にある小さな動物園。最後の一匹の動物が死んでしまい、園長は飼育員の松田に新たな動物を探すことを命じる。集まってきたのは猛獣の女の子たちだった…。",
  "date": "2014-10-22",
  "platform": "WEB",
  "images": {
    "large": "//lain.bgm.tv/pic/cover/l/c1/c8/110641_vvzpb.jpg",
    "common": "//lain.bgm.tv/r/400/pic/cover/l/c1/c8/110641_vvzpb.jpg"
  },
  "eps": 10,
  "rating": {
    "rank": 5079,
    "total": 141,
    "count": {
      "1": 1,
      "2": 1,
      "3": 1,
      "4": 2,
      "5": 27,
      "6": 58,
      "7": 31,
      "8": 14,
      "9": 2,
      "10": 4
    },
    "score": 6.3
  },
  "tags": [
    {
      "name": "泡面番",
      "count": 67
    },
    {
      "name": "Ordet",
      "count": 28
    },
    {
      "name": "2014",
      "count": 26
    },
    {
      "name": "Wake_Up_Girls!",
      "count": 25
    },
    {
      "name": "2014年10月",
      "count": 21
    },
    {
      "name": "WEB",
      "count": 21
    },
    {
      "name": "原创",
      "count": 20
    },
    {
      "name": "百合",
      "count": 16
    },
    {
      "name": "搞笑",
      "count": 13
    },
    {
      "name": "wug",
      "count": 12
    },
    {
      "name": "偶像",
      "count": 10
    },
    {
      "name": "FANS向",
      "count": 6
    },
    {
      "name": "TV",
      "count": 6
    },
    {
      "name": "泡面",
      "count": 5
    },
    {
      "name": "哭穷",
      "count": 5
    },
    {
      "name": "2014年9月",
      "count": 4
    },
    {
      "name": "森井ケンシロウ",
      "count": 3
    },
    {
      "name": "ダブトゥーンスタジオ",
      "count": 3
    },
    {
      "name": "山本宽",
      "count": 2
    },
    {
      "name": "短片",
      "count": 2
    },
    {
      "name": "2014年",
      "count": 2
    },
    {
      "name": "森井健史郎",
      "count": 2
    },
    {
      "name": "W-toonStudio",
      "count": 2
    },
    {
      "name": "待田堂子",
      "count": 2
    },
    {
      "name": "山下七海",
      "count": 1
    },
    {
      "name": "冈笃志",
      "count": 1
    },
    {
      "name": "吉岡茉祐",
      "count": 1
    },
    {
      "name": "松田惠里子",
      "count": 1
    },
    {
      "name": "吉冈茉祐",
      "count": 1
    },
    {
      "name": "二〇一四年",
      "count": 1
    }
  ],
  "locked": false,
  "sites": [
    {
      "site": "bangumi",
      "id": "110641"
    },
    {
      "site": "unext",
      "id": "SID0003286",
      "begin": "2019-04-12T03:00:00.000Z",
      "broadcast": "R/2019-04-12T03:00:00.000Z/P7D"
    }
  ]
}