{
  "id": 102140,
  "name": "対魔導学園35試験小隊",
  "name_cn": "对魔导学园35试验小队",
  "summary": "在人类逐渐无法使用魔法的世界里，人们为了对付还拥有残存魔力的人类，成立了培训“异端审问官”的机关“对魔导学园”。主角草剃哮在这个以枪械为主要武器的环境里，仍旧使用刀剑战斗，而他所率领的第35试验小队，更是由一群劣等生所组成，甚至有“虾兵蟹将小队”之称。某日，身为顶尖“魔女猎人”的超精英枪械高手凤樱花加入了这只小队，让第35试验小队开始有了改变。",
  "date": "2015-10-07",
  "platform": "TV",
  "images": {
    "large": "//lain.bgm.tv/pic/cover/l/3c/c7/102140_HmD0O.jpg",
    "common": "//lain.bgm.tv/r/400/pic/cover/l/3c/c7/102140_HmD0O.jpg"
  },
  "eps": 12,
  "rating": {
    "rank": 7554,
    "total": 1679,
    "count": {
      "1": 12,
      "2": 13,
      "3": 38,
      "4": 123,
      "5": 404,
      "6": 724,
      "7": 278,
      "8": 67,
      "9": 5,
      "10": 15
    },
    "score": 5.8
  },
  "tags": [
    {
      "name": "轻小说改",
      "count": 379
    },
    {
      "name": "后宫",
      "count": 360
    },
    {
      "name": "2015年10月",
      "count": 353
    },
    {
      "name": "TV",
      "count": 212
    },
    {
      "name": "战斗",
      "count": 174
    },
    {
      "name": "SILVERLINK.",
      "count": 174
    },
    {
      "name": "对魔导学园35试验小队",
      "count": 170
    },
    {
      "name": "轻改",
      "count": 127
    },
    {
      "name": "2015",
      "count": 95
    },
    {
      "name": "奇幻",
      "count": 69
    },
    {
      "name": "SILVERLINK",
      "count": 62
    },
    {
      "name": "细谷佳正",
      "count": 31
    },
    {
      "name": "河村智之",
      "count": 23
    },
    {
      "name": "校园",
      "count": 23
    },
    {
      "name": "2015年",
      "count": 9
    },
    {
      "name": "魔法",
      "count": 7
    },
    {
      "name": "大久保瑠美",
      "count": 6
    },
    {
      "name": "SILVER_LINK.",
      "count": 5
    },
    {
      "name": "伊藤かな恵",
      "count": 5
    },
    {
      "name": "日本动画",
      "count": 5
    },
    {
      "name": "小说改",
      "count": 5
    },
    {
      "name": "2015秋",
      "count": 4
    },
    {
      "name": "热血",
      "count": 4
    },
    {
      "name": "搞笑",
      "count": 3
    },
    {
      "name": "細谷佳正",
      "count": 3
    },
    {
      "name": "季番",
      "count": 3
    },
    {
      "name": "白石涼子",
      "count": 3
    },
    {
      "name": "下山健人",
      "count": 3
    },
    {
      "name": "装逼",
      "count": 2
    },
    {
      "name": "动画",
      "count": 2
    }
  ],
  "locked": false,
  "sites": [
    {
      "site": "bilibili",
      "id": "2724",
      "begin": "2015-10-07T17:35:00.000Z",
      "broadcast": "R/2015-10-07T17:35:00.000Z/P7D"
    },
    {
      "site": "youku",
      "id": "701b312855fc11e5b5ce",
      "begin": "2015-10-07T17:35:00.000Z"
    },
    {
      "site": "bangumi",
      "id": "102140"
    },
    {
      "site": "nicovideo",
      "id": "35shoutai",
      "begin": "2015-10-24T03:00:00.000Z",
      "broadcast": "R/2015-10-24T03:00:00.000Z/P7D"
    },
    {
      "site": "iqiyi",
      "id": "a_19rrh82xr9",
      "begin": "2017-06-30T16:02:47.000Z"
    },
    {
      "site": "qq",
      "id": "d/d6kv8937dpgs0ol",
      "begin": ""
    },
    {
      "site": "ani_one_asia",
      "id": "PLxSscENEp7JgwaK0wn3LU8SGVK4mC9YSe",
      "begin": "",
      "broadcast": ""
    },
    {
      "site": "unext",
      "id": "SID0020231",
      "begin": "2015-10-24T03:00:00.000Z",
      "broadcast": "R/2015-10-24T03:00:00.000Z/P7D"
    },
    {
      "site": "dmhy",
      "id": "35+試"
    },
    {
      "site": "mikan",
      "id": "616"
    }
  ]
}