{
  "id": 472554,
  "name": "モブから始まる探索英雄譚",
  "name_cn": "从路人角色开始的探索英雄谭",
  "summary": "モブな男子高校生の成り上がり英雄譚！\r\nステータスも低くいわゆるモブキャラである\r\n高校生・高木海斗は、\r\n日本に現れたダンジョンで毎日スライムを狩り、\r\nクラスのマドンナである幼馴染に憧れながらせっせと\r\n小遣稼ぎをするふつうの探索者だった。\r\nある日そんな彼の前に、見たこともない金色のスライムが現れる。\r\n困惑しつつも倒すと、神話の存在を呼び出せる\r\nサーバントカードと呼ばれる\r\n時価数億の激レアアイテムが!!\r\n覚悟を決めて召喚するとそこには\r\nこの世のものとも思えぬ美しさの戦乙女(ヴァルキリー)が現れ――。\r\n モブな探索者から成り上がれ！ 現代バトルファンタジー開幕！",
  "date": "2024-07-06",
  "platform": "TV",
  "images": {
    "large": "//lain.bgm.tv/pic/cover/l/65/1c/472554_eh55w.jpg",
    "common": "//lain.bgm.tv/r/400/pic/cover/l/65/1c/472554_eh55w.jpg"
  },
  "eps": 11,
  "rating": {
    "rank": 8411,
    "total": 261,
    "count": {
      "1": 11,
      "2": 7,
      "3": 36,
      "4": 66,
      "5": 73,
      "6": 46,
      "7": 13,
      "8": 6,
      "9": 2,
      "10": 1
    },
    "score": 4.6
  },
  "tags": [
    {
      "name": "2024年7月",
      "count": 131
    },
    {
      "name": "轻小说改",
      "count": 91
    },
    {
      "name": "奇幻",
      "count": 72
    },
    {
      "name": "TV",
      "count": 61
    },
    {
      "name": "战斗",
      "count": 48
    },
    {
      "name": "2024",
      "count": 44
    },
    {
      "name": "萝莉",
      "count": 37
    },
    {
      "name": "月虹",
      "count": 36
    },
    {
      "name": "厕纸",
      "count": 28
    },
    {
      "name": "花澤香菜",
      "count": 27
    },
    {
      "name": "小说改",
      "count": 23
    },
    {
      "name": "轻改",
      "count": 22
    },
    {
      "name": "日本动画",
      "count": 17
    },
    {
      "name": "小林智樹",
      "count": 14
    },
    {
      "name": "龙傲天",
      "count": 4
    },
    {
      "name": "异世界",
      "count": 4
    },
    {
      "name": "未定档",
      "count": 3
    },
    {
      "name": "保住有哉",
      "count": 3
    },
    {
      "name": "2024年",
      "count": 3
    },
    {
      "name": "后宫",
      "count": 2
    },
    {
      "name": "和氣あず未",
      "count": 2
    },
    {
      "name": "冒险",
      "count": 2
    },
    {
      "name": "日常",
      "count": 2
    },
    {
      "name": "TVA",
      "count": 2
    },
    {
      "name": "a.Anime",
      "count": 1
    },
    {
      "name": "惨遭动画化",
      "count": 1
    },
    {
      "name": "k.坚持了几集所以勉强多给一星(2星)",
      "count": 1
    },
    {
      "name": "f.日本",
      "count": 1
    },
    {
      "name": "男主是弱智吗？",
      "count": 1
    },
    {
      "name": "从路人角色开始的探索英雄谭",
      "count": 1
    }
  ],
  "locked": false
}