{
  "id": 187513,
  "name": "聖ルミナス女学院",
  "name_cn": "圣路美娜女学院",
  "summary": "17歳の高校生・木島海平は亡き祖父木島綿平の遺言で聖ルミナス女学院の新理事長を引き受けることになった。\r\nその頃学院では、メリナ・スカフィシがシャワー室から失踪するという事件が発生していた。海平は友人の龍三、従妹の糊湖、その友人の良子らと共に学院中を探し回るが、そんな彼らを嘲笑うかの如く次々と学院内の少女達が消失する事件が発生する。さらに海平の前に謎の少年と老婆（鈴吉萌絵）が現れ、海平に渡された祖父の遺品のポケットベルには謎めいた不可解なメッセージが送られる。そして彼の与り知らない所で密かにある計画が進められていた。",
  "date": "1998-10-05",
  "platform": "TV",
  "images": {
    "large": "//lain.bgm.tv/pic/cover/l/c8/12/187513_SzWw3.jpg",
    "common": "//lain.bgm.tv/r/400/pic/cover/l/c8/12/187513_SzWw3.jpg"
  },
  "eps": 13,
  "rating": {
    "rank": 0,
    "total": 4,
    "count": {
      "1": 0,
      "2": 0,
      "3": 0,
      "4": 1,
      "5": 1,
      "6": 1,
      "7": 1,
      "8": 0,
      "9": 0,
      "10": 0
    },
    "score": 5.5
  },
  "tags": [
    {
      "name": "1998",
      "count": 4
    },
    {
      "name": "TV",
      "count": 3
    },
    {
      "name": "6",
      "count": 1
    },
    {
      "name": "旧番",
      "count": 1
    },
    {
      "name": "TriangleStaff",
      "count": 1
    },
    {
      "name": "桶谷顕",
      "count": 1
    },
    {
      "name": "アミノテツロー",
      "count": 1
    },
    {
      "name": "旧物",
      "count": 1
    },
    {
      "name": "冷门老番",
      "count": 1
    },
    {
      "name": "1998年十月番",
      "count": 1
    },
    {
      "name": "有空再補1",
      "count": 1
    },
    {
      "name": "1998年10月",
      "count": 1
    },
    {
      "name": "保志総一朗",
      "count": 1
    },
    {
      "name": "日本动画",
      "count": 1
    },
    {
      "name": "OVA",
      "count": 1
    },
    {
      "name": "TVA",
      "count": 1
    },
    {
      "name": "トライアングルスタッフ",
      "count": 1
    },
    {
      "name": "1998年",
      "count": 1
    },
    {
      "name": "飯塚雅弓",
      "count": 1
    },
    {
      "name": "岩永哲哉",
      "count": 1
    }
  ],
  "locked": false,
  "sites": [
    {
      "site": "bangumi",
      "id": "187513"
    },
    {
      "site": "unext",
      "id": "SID0047509",
      "begin": "2020-05-02T03:00:00.000Z",
      "broadcast": "R/2020-05-02T03:00:00.000Z/P7D"
    }
  ]
}