{
  "id": 2481,
  "name": "宇宙の騎士テッカマンブレード",
  "name_cn": "宇宙骑士BLADE",
  "summary": "联合地球历192年，神秘宇宙生命体侵略地球。外宇宙开发基地意外的搭救了一个从天而降的奇怪人类，而他居然可以变身为身着坚硬盔甲的战士和怪兽进行抗衡。濒临灭亡的人类还是抓住了这根救命稻草，天外来客以D-boy（Dangerous boy）的身份在外宇宙开发基地留了下来，经历多次拯救地球的战斗后，人类把他称为宇宙骑士。",
  "date": "1992-02-18",
  "platform": "TV",
  "images": {
    "large": "//lain.bgm.tv/pic/cover/l/6b/57/2481_msJP0.jpg",
    "common": "//lain.bgm.tv/r/400/pic/cover/l/6b/57/2481_msJP0.jpg"
  },
  "eps": 49,
  "rating": {
    "rank": 303,
    "total": 705,
    "count": {
      "1": 3,
      "2": 1,
      "3": 1,
      "4": 3,
      "5": 11,
      "6": 53,
      "7": 140,
      "8": 272,
      "9": 161,
      "10": 60
    },
    "score": 7.9
  },
  "tags": [
    {
      "name": "宇宙骑士",
      "count": 189
    },
    {
      "name": "D-BOY",
      "count": 141
    },
    {
      "name": "龙之子",
      "count": 124
    },
    {
      "name": "TV",
      "count": 111
    },
    {
      "name": "萝卜",
      "count": 108
    },
    {
      "name": "1992",
      "count": 107
    },
    {
      "name": "童年",
      "count": 104
    },
    {
      "name": "经典",
      "count": 80
    },
    {
      "name": "科幻",
      "count": 75
    },
    {
      "name": "机战",
      "count": 61
    },
    {
      "name": "悲情",
      "count": 52
    },
    {
      "name": "原创",
      "count": 51
    },
    {
      "name": "林原惠",
      "count": 32
    },
    {
      "name": "神音乐",
      "count": 26
    },
    {
      "name": "机器人",
      "count": 19
    },
    {
      "name": "90年代",
      "count": 9
    },
    {
      "name": "空战",
      "count": 8
    },
    {
      "name": "ねぎしひろし",
      "count": 7
    },
    {
      "name": "龙之子Production",
      "count": 7
    },
    {
      "name": "森川智之",
      "count": 6
    },
    {
      "name": "タツノコプロ",
      "count": 6
    },
    {
      "name": "根岸弘",
      "count": 5
    },
    {
      "name": "あかほりさとる",
      "count": 4
    },
    {
      "name": "年番",
      "count": 4
    },
    {
      "name": "1992年",
      "count": 4
    },
    {
      "name": "竜の子プロダクション",
      "count": 3
    },
    {
      "name": "致郁",
      "count": 3
    },
    {
      "name": "儿时回忆",
      "count": 3
    },
    {
      "name": "和田薫",
      "count": 3
    },
    {
      "name": "关岛真赖",
      "count": 3
    }
  ],
  "locked": false,
  "sites": [
    {
      "site": "bangumi",
      "id": "2481"
    },
    {
      "site": "unext",
      "id": "SID0003345",
      "begin": "2019-08-27T03:00:00.000Z",
      "broadcast": "R/2019-08-27T03:00:00.000Z/P7D"
    }
  ]
}