{
  "id": 47957,
  "name": "超次元ゲイム ネプテューヌ THE ANIMATION",
  "name_cn": "超次元游戏 海王星",
  "summary": "ここは、ゲイムギョウ界。「女神」と呼ばれる存在が国を司る、現実とは異なる世界である。\r\n四人の女神が統治する四つの国家の名前は、プラネテューヌ、ラステイション、ルウィー、リーンボックス。\r\n各国の間では、女神の力の源「シェア」をめぐる争いが、長年にわたって続けられてきた。\r\nしかし、互いの国力をいたずらに削る状況を危惧した女神たちは、シェアを武力で奪うことを禁じる「友好条約」を結ぶ。\r\n友好条約のもと、新たな関係への一歩を踏み出す四人の女神たちと、その妹たち。ときに笑い合い、ときにぶつかり合い、\r\nときに手を取り合う、カラフルな日々の幕が開ける。\r\nゲイムギョウ界には、どんな明日が待っているのだろうか——。",
  "date": "2013-07-12",
  "platform": "TV",
  "images": {
    "large": "//lain.bgm.tv/pic/cover/l/c6/f0/47957_PB0en.jpg",
    "common": "//lain.bgm.tv/r/400/pic/cover/l/c6/f0/47957_PB0en.jpg"
  },
  "eps": 13,
  "rating": {
    "rank": 4108,
    "total": 1950,
    "count": {
      "1": 4,
      "2": 2,
      "3": 11,
      "4": 42,
      "5": 181,
      "6": 595,
      "7": 739,
      "8": 284,
      "9": 55,
      "10": 37
    },
    "score": 6.7
  },
  "tags": [
    {
      "name": "游戏改",
      "count": 520
    },
    {
      "name": "2013年7月",
      "count": 381
    },
    {
      "name": "超次元游戏",
      "count": 360
    },
    {
      "name": "百合",
      "count": 345
    },
    {
      "name": "萌",
      "count": 249
    },
    {
      "name": "TV",
      "count": 243
    },
    {
      "name": "海王星",
      "count": 197
    },
    {
      "name": "2013",
      "count": 144
    },
    {
      "name": "davidproduction",
      "count": 141
    },
    {
      "name": "田中理恵",
      "count": 114
    },
    {
      "name": "阿澄佳奈",
      "count": 104
    },
    {
      "name": "佐藤利奈",
      "count": 72
    },
    {
      "name": "堀江由衣",
      "count": 71
    },
    {
      "name": "今井麻美",
      "count": 51
    },
    {
      "name": "战斗",
      "count": 25
    },
    {
      "name": "奇幻",
      "count": 22
    },
    {
      "name": "植田佳奈",
      "count": 22
    },
    {
      "name": "david_production",
      "count": 16
    },
    {
      "name": "搞笑",
      "count": 15
    },
    {
      "name": "向井雅浩",
      "count": 14
    },
    {
      "name": "喜多村英梨",
      "count": 12
    },
    {
      "name": "日常",
      "count": 12
    },
    {
      "name": "萝莉",
      "count": 9
    },
    {
      "name": "超次元游戏海王星",
      "count": 8
    },
    {
      "name": "萌豚",
      "count": 8
    },
    {
      "name": "小仓唯",
      "count": 7
    },
    {
      "name": "卖肉",
      "count": 7
    },
    {
      "name": "田中理惠",
      "count": 6
    },
    {
      "name": "花泽香菜",
      "count": 6
    },
    {
      "name": "游改",
      "count": 6
    }
  ],
  "locked": false
}