{
  "id": 259877,
  "name": "イナズマイレブン オリオンの刻印",
  "name_cn": "闪电十一人 俄里翁的刻印",
  "summary": "ついに「世界への門」が開く！\r\n\r\n少年サッカー日本代表「イナズマジャパン」がついに発表！\r\nその中には、稲森明日人、灰崎凌兵、野坂悠馬の名前もあった。\r\n各校から選び抜かれた精鋭選手が集結する。\r\nさらに、海外のクラブチームでプレイしていた新たな仲間「一星充」を加え、\r\n今まさに少年サッカー日本代表は、世界の荒波へと船出する。\r\n\r\nしかし、その先は予想をはるかに超える試練が待っていた。\r\n謎のプレイヤー“オリオンの使徒”\r\n策略、裏切り、衝突---\r\n\r\n様々な思惑が渦巻く少年サッカー世界大会\r\nFFI（フットボールフロンティア・インターナショナル）が\r\n今、始まる。\r\n\r\n日本（にっぽん）よ！世界へ羽ばたけ！",
  "date": "2018-10-05",
  "platform": "TV",
  "images": {
    "large": "//lain.bgm.tv/pic/cover/l/11/3e/259877_mhm0v.jpg",
    "common": "//lain.bgm.tv/r/400/pic/cover/l/11/3e/259877_mhm0v.jpg"
  },
  "eps": 49,
  "rating": {
    "rank": 0,
    "total": 21,
    "count": {
      "1": 3,
      "2": 0,
      "3": 4,
      "4": 2,
      "5": 6,
      "6": 4,
      "7": 2,
      "8": 0,
      "9": 0,
      "10": 0
    },
    "score": 4.3
  },
  "tags": [
    {
      "name": "OLM",
      "count": 11
    },
    {
      "name": "2018年10月",
      "count": 11
    },
    {
      "name": "闪电十一人",
      "count": 7
    },
    {
      "name": "TV",
      "count": 6
    },
    {
      "name": "2018",
      "count": 5
    },
    {
      "name": "日野晃博",
      "count": 5
    },
    {
      "name": "俄里翁的刻印",
      "count": 4
    },
    {
      "name": "日本动画",
      "count": 3
    },
    {
      "name": "鎌倉由実",
      "count": 2
    },
    {
      "name": "村瀬歩",
      "count": 2
    },
    {
      "name": "竞技",
      "count": 2
    },
    {
      "name": "OLMTEAMOTA",
      "count": 1
    },
    {
      "name": "日本",
      "count": 1
    },
    {
      "name": "神谷浩史",
      "count": 1
    },
    {
      "name": "运动",
      "count": 1
    },
    {
      "name": "福山潤",
      "count": 1
    },
    {
      "name": "动画",
      "count": 1
    },
    {
      "name": "游戏改",
      "count": 1
    },
    {
      "name": "子供向",
      "count": 1
    },
    {
      "name": "TVA",
      "count": 1
    }
  ],
  "locked": false
}