{
  "id": 2566,
  "name": "11eyes",
  "name_cn": "",
  "summary": "失去姐姐而过著懒散生活的男主角・皋月驱和他的青梅竹马水奈瀬ゆか，突然一同被卷入一个染红的世界。然而，与另外4位来自相同世界少年少女一同被卷入到这个事件中，并且已打倒黑骑士们为目的。为了生存下去，并结束“赤之夜，他们与黑骑士们的战斗也就此开始",
  "date": "2009-10-06",
  "platform": "TV",
  "images": {
    "large": "//lain.bgm.tv/pic/cover/l/42/fe/2566_M2Bsq.jpg",
    "common": "//lain.bgm.tv/r/400/pic/cover/l/42/fe/2566_M2Bsq.jpg"
  },
  "eps": 12,
  "rating": {
    "rank": 8268,
    "total": 1649,
    "count": {
      "1": 38,
      "2": 46,
      "3": 101,
      "4": 289,
      "5": 422,
      "6": 473,
      "7": 199,
      "8": 59,
      "9": 9,
      "10": 13
    },
    "score": 5.2
  },
  "tags": [
    {
      "name": "11eyes",
      "count": 450
    },
    {
      "name": "后宫之眼",
      "count": 181
    },
    {
      "name": "TV",
      "count": 172
    },
    {
      "name": "后宫",
      "count": 149
    },
    {
      "name": "2009年10月",
      "count": 110
    },
    {
      "name": "面目全非",
      "count": 108
    },
    {
      "name": "志仓千代丸",
      "count": 106
    },
    {
      "name": "2009",
      "count": 96
    },
    {
      "name": "GAL改",
      "count": 91
    },
    {
      "name": "小野大辅",
      "count": 88
    },
    {
      "name": "扭曲的爱",
      "count": 70
    },
    {
      "name": "lass",
      "count": 64
    },
    {
      "name": "5pb.",
      "count": 54
    },
    {
      "name": "卖萌不好玩",
      "count": 36
    },
    {
      "name": "彩音",
      "count": 35
    },
    {
      "name": "动画工房",
      "count": 34
    },
    {
      "name": "游戏改",
      "count": 29
    },
    {
      "name": "奇幻",
      "count": 20
    },
    {
      "name": "後藤麻衣",
      "count": 19
    },
    {
      "name": "人渣诚",
      "count": 14
    },
    {
      "name": "安玖深音",
      "count": 12
    },
    {
      "name": "战斗",
      "count": 12
    },
    {
      "name": "校园",
      "count": 10
    },
    {
      "name": "2009年",
      "count": 9
    },
    {
      "name": "下田正美",
      "count": 8
    },
    {
      "name": "動画工房",
      "count": 8
    },
    {
      "name": "浅川悠",
      "count": 5
    },
    {
      "name": "看看",
      "count": 5
    },
    {
      "name": "恋爱",
      "count": 5
    },
    {
      "name": "动画",
      "count": 4
    }
  ],
  "locked": false
}